pyspace/__init__.py
pyspace/esa/__init__.py
pyspace/esa/mortality_natality.py
pyspace/esa/opendata.py
pyspace/jaxa/__init__.py
pyspace/jaxa/gosat.py
pyspace/nasa/__init__.py
pyspace/nasa/atmospheric.py
pyspace/nasa/earthdata_login.py
pyspace/nasa/landslide.py
pyspace_api-0.0.1.dist-info/LICENSE
pyspace_api-0.0.1.dist-info/METADATA
pyspace_api-0.0.1.dist-info/WHEEL
pyspace_api-0.0.1.dist-info/top_level.txt
pyspace_api-0.0.1.dist-info/RECORD
